src/__init__.py
src/commands/__init__.py
src/commands/image.py
src/main.py
zyx_utils-0.1.1.dist-info/LICENSE
zyx_utils-0.1.1.dist-info/METADATA
zyx_utils-0.1.1.dist-info/WHEEL
zyx_utils-0.1.1.dist-info/entry_points.txt
zyx_utils-0.1.1.dist-info/RECORD
