Metadata-Version: 2.1
Name: zyx-utils
Version: 0.1.1
Summary: A collection of utility scripts
License: MIT
Author: Loki
Author-email: yongxiang.zhan@outlook.com
Requires-Python: >=3.11,<4.0
Classifier: License :: OSI Approved :: MIT License
Classifier: Programming Language :: Python :: 3
Classifier: Programming Language :: Python :: 3.11
Classifier: Programming Language :: Python :: 3.12
Requires-Dist: pillow (>=11.1.0,<12.0.0)
Requires-Dist: requests (>=2.32.3,<3.0.0)
Requires-Dist: typer (>=0.15.2,<0.16.0)
